llmring/__init__.py
llmring/base.py
llmring/cli.py
llmring/cli_utils.py
llmring/constants.py
llmring/exceptions.py
llmring/file_utils.py
llmring/llmring.lock
llmring/lockfile_core.py
llmring/receipts.py
llmring/registry.py
llmring/schemas.py
llmring/server_client.py
llmring/service.py
llmring/service_extended.py
llmring/token_counter.py
llmring/lockfile/__init__.py
llmring/logging/__init__.py
llmring/logging/decorators.py
llmring/logging/normalizers.py
llmring/mcp/__init__.py
llmring/mcp/http_client.py
llmring/mcp/client/__init__.py
llmring/mcp/client/cli.py
llmring/mcp/client/conversation_manager_async.py
llmring/mcp/client/enhanced_llm.py
llmring/mcp/client/file_utils.py
llmring/mcp/client/info_service.py
llmring/mcp/client/llm_client.py
llmring/mcp/client/llmring_integration.py
llmring/mcp/client/mcp_client.py
llmring/mcp/client/pool_config.py
llmring/mcp/client/stateless_engine.py
llmring/mcp/client/streaming_handler.py
llmring/mcp/client/chat/__init__.py
llmring/mcp/client/chat/app.py
llmring/mcp/client/chat/styles.py
llmring/mcp/client/models/__init__.py
llmring/mcp/client/models/schemas.py
llmring/mcp/client/scripts/__init__.py
llmring/mcp/client/scripts/list_models.py
llmring/mcp/client/scripts/setup.py
llmring/mcp/client/transports/__init__.py
llmring/mcp/client/transports/base.py
llmring/mcp/client/transports/factory.py
llmring/mcp/client/transports/http.py
llmring/mcp/client/transports/sse.py
llmring/mcp/client/transports/stdio.py
llmring/mcp/client/transports/streamable_http.py
llmring/mcp/server/__init__.py
llmring/mcp/server/main.py
llmring/mcp/server/mcp_server.py
llmring/mcp/server/examples/__init__.py
llmring/mcp/server/examples/math_tools.py
llmring/mcp/server/integrations/__init__.py
llmring/mcp/server/integrations/fastapi_streamable.py
llmring/mcp/server/interfaces/__init__.py
llmring/mcp/server/interfaces/auth.py
llmring/mcp/server/interfaces/middleware.py
llmring/mcp/server/interfaces/storage.py
llmring/mcp/server/lockfile_server/__init__.py
llmring-1.1.1.dist-info/METADATA
llmring-1.1.1.dist-info/WHEEL
llmring-1.1.1.dist-info/entry_points.txt
llmring-1.1.1.dist-info/licenses/LICENSE
llmring-1.1.1.dist-info/RECORD
