Metadata-Version: 2.4
Name: llmring
Version: 1.1.1
Summary: Unified Python interface for OpenAI, Anthropic, Google, and Ollama LLMs
Project-URL: Homepage, https://llmring.ai
Project-URL: Documentation, https://github.com/juanre/llmring
Project-URL: Repository, https://github.com/juanre/llmring
Project-URL: Issues, https://github.com/juanre/llmring/issues
Author-email: Juan Reyero <juan@juanreyero.com>
Maintainer-email: Juan Reyero <juan@juanreyero.com>
License: MIT
License-File: LICENSE
Keywords: ai,anthropic,api,claude,gemini,gpt,llm,ollama,openai
Classifier: Development Status :: 4 - Beta
Classifier: Intended Audience :: Developers
Classifier: License :: OSI Approved :: MIT License
Classifier: Programming Language :: Python :: 3
Classifier: Programming Language :: Python :: 3.11
Classifier: Programming Language :: Python :: 3.12
Classifier: Programming Language :: Python :: 3.13
Classifier: Topic :: Scientific/Engineering :: Artificial Intelligence
Classifier: Topic :: Software Development :: Libraries :: Python Modules
Requires-Python: >=3.11
Requires-Dist: aiohttp>=3.8.0
Requires-Dist: anthropic>=0.67.0
Requires-Dist: cachetools>=5.5.2
Requires-Dist: click>=8.2.1
Requires-Dist: cryptography>=41.0.0
Requires-Dist: google-genai>=0.1.0
Requires-Dist: httpx>=0.24.0
Requires-Dist: jsonschema>=4.0.0
Requires-Dist: ollama>=0.4.0
Requires-Dist: openai>=1.99.0
Requires-Dist: prompt-toolkit>=3.0.51
Requires-Dist: pydantic>=2.0.0
Requires-Dist: python-dotenv>=1.0.0
Requires-Dist: rich>=14.1.0
Requires-Dist: tenacity>=9.1.2
Requires-Dist: tiktoken>=0.5.0
Requires-Dist: toml>=0.10.2
Requires-Dist: typing-extensions>=4.14.1
Requires-Dist: websockets>=15.0.1
Provides-Extra: http
Requires-Dist: fastapi>=0.100.0; extra == 'http'
Requires-Dist: uvicorn>=0.30.0; extra == 'http'
